nepo-0.3.1.dist-info/DESCRIPTION.rst
nepo-0.3.1.dist-info/METADATA
nepo-0.3.1.dist-info/RECORD
nepo-0.3.1.dist-info/WHEEL
nepo-0.3.1.dist-info/entry_points.txt
nepo-0.3.1.dist-info/metadata.json
nepo-0.3.1.dist-info/top_level.txt
src/__init__.py
src/cli.py
src/core.py
src/manifest.py
