Metadata-Version: 2.0
Name: nepo
Version: 0.3.1
Summary: universal url opener
Home-page: https://github.com/foutoucour/nepo
Author: Jordi Riera
Author-email: kender@gmail.com
License: MIT
Platform: UNKNOWN
Classifier: License :: OSI Approved :: MIT License
Classifier: Programming Language :: Python
Classifier: Programming Language :: Python :: Implementation :: CPython
Requires-Dist: click
Requires-Dist: click-didyoumean
Requires-Dist: click-help-colors
Requires-Dist: crayons
